pymerkletree/__init__.py
pymerkletree/merkle.py
pymerkletree-1.0.6.dist-info/METADATA
pymerkletree-1.0.6.dist-info/RECORD
pymerkletree-1.0.6.dist-info/WHEEL
pymerkletree-1.0.6.dist-info/top_level.txt
tests/__init__.py
tests/test_merkle.py
