Metadata-Version: 2.1
Name: pymerkletree
Version: 1.0.6
Summary: Simple Merkle Tree
Home-page: https://github.com/aliciawyy/pymerkletools
Author: Alice Wang, Eder Santana
Author-email: rainingilove@gmail.com
License: MIT
Keywords: merkle tree,blockchain
Platform: UNKNOWN
Classifier: Intended Audience :: Developers
Classifier: Intended Audience :: Education
Classifier: Intended Audience :: Science/Research
Classifier: License :: OSI Approved :: MIT License
Classifier: Programming Language :: Python :: 2.7
Classifier: Programming Language :: Python :: 3.5
Classifier: Programming Language :: Python :: 3.6
Classifier: Topic :: Software Development :: Libraries
Classifier: Topic :: Software Development :: Libraries :: Python Modules
Requires-Dist: pysha3 (>=1.0b1)
